idiff/__init__.py
idiff/simple.py
idiff-0.0.1.dist-info/LICENCE
idiff-0.0.1.dist-info/METADATA
idiff-0.0.1.dist-info/WHEEL
idiff-0.0.1.dist-info/top_level.txt
idiff-0.0.1.dist-info/RECORD
