Metadata-Version: 2.1
Name: idiff
Version: 0.0.1
Summary: Improve 2D powder diffraction patterns
Home-page: https://github.com/mirekslouf/idiff/
Author: Mirek Slouf
Author-email: mirek.slouf@gmail.com
License: MIT
Project-URL: Documentation, https://mirekslouf.github.io/idiff/
Classifier: Programming Language :: Python :: 3
Classifier: License :: OSI Approved :: MIT License
Classifier: Operating System :: OS Independent
Requires-Python: >=3.6
License-File: LICENCE
